fedbiomed_cli/__init__.py
fedbiomed_cli/data_manager.py
fedbiomed_cli/json.py
fedbiomed_cli/mqtt.py
fedbiomed_cli/tasks.py
fedbiomed_cli/utils/__init__.py
fedbiomed_cli/utils/cli.py
fedbiomed_cli/utils/requests.py
fedbiomed_cli-0.1.8.dist-info/entry_points.txt
fedbiomed_cli-0.1.8.dist-info/WHEEL
fedbiomed_cli-0.1.8.dist-info/METADATA
fedbiomed_cli-0.1.8.dist-info/RECORD
