Metadata-Version: 2.1
Name: fedbiomed-cli
Version: 0.1.8
Summary: 
Author: Santiago SILVA
Author-email: 16252054+sssilvar@users.noreply.github.com
Requires-Python: >=3.8,<4.0
Classifier: Programming Language :: Python :: 3
Classifier: Programming Language :: Python :: 3.8
Classifier: Programming Language :: Python :: 3.9
Requires-Dist: GitPython (>=3.1.14,<4.0.0)
Requires-Dist: monai (>=0.4.0,<0.5.0)
Requires-Dist: paho-mqtt (>=1.5.1,<2.0.0)
Requires-Dist: pandas (>=1.2.3,<2.0.0)
Requires-Dist: persist-queue (>=0.5.1,<0.6.0)
Requires-Dist: pytorch-ignite (>=0.4.4,<0.5.0)
Requires-Dist: requests (>=2.25.1,<3.0.0)
Requires-Dist: tabulate (>=0.8.9,<0.9.0)
Requires-Dist: tinydb (>=4.4.0,<5.0.0)
Requires-Dist: torch (>=1.8.0,<2.0.0)
Requires-Dist: torchvision (>=0.9.0,<0.10.0)
Requires-Dist: tqdm (>=4.59.0,<5.0.0)
Requires-Dist: validators (>=0.18.2,<0.19.0)
